[
  {
    "date": "2026-04-07",
    "followers": 5183
  },
  {
    "date": "2026-04-14",
    "followers": 5215
  },
  {
    "date": "2026-04-21",
    "followers": 5226
  },
  {
    "date": "2026-04-22",
    "followers": 5227
  },
  {
    "date": "2026-04-23",
    "followers": 5228
  },
  {
    "date": "2026-04-24",
    "followers": 5228
  },
  {
    "date": "2026-04-25",
    "followers": 5228
  },
  {
    "date": "2026-04-26",
    "followers": 5235
  },
  {
    "date": "2026-04-27",
    "followers": 5242
  },
  {
    "date": "2026-04-28",
    "followers": 5249
  }
]